openXJV/__init__.py
openXJV/__main__.py
openXJV/bin/__init__.py
openXJV/bin/openXJV.py
openXJV/bin/codelisten_json/Aussonderungsart_1.0.json
openXJV/bin/codelisten_json/Bewertungsvorschlag_1.0.json
openXJV/bin/codelisten_json/BfJ_Staat_6.1.json
openXJV/bin/codelisten_json/Bundesland_2010-04-01.json
openXJV/bin/codelisten_json/Country_Codes_8.json
openXJV/bin/codelisten_json/Datentyp_1.1.json
openXJV/bin/codelisten_json/GDS.Aktenreferenzart_2.1.json
openXJV/bin/codelisten_json/GDS.Aktentyp_2.2.json
openXJV/bin/codelisten_json/GDS.Aktenzeichenart_2.0.json
openXJV/bin/codelisten_json/GDS.Anschriftstyp_3.0.json
openXJV/bin/codelisten_json/GDS.Auskunft.Vollstreckungssachen.Fehler_1.0.json
openXJV/bin/codelisten_json/GDS.Ausweisart_1.0.json
openXJV/bin/codelisten_json/GDS.BRIS-ListOfRegisters_1.0.json
openXJV/bin/codelisten_json/GDS.BRIS-ListOfRegisters_2.0.json
openXJV/bin/codelisten_json/GDS.Bestandteiltyp_2.4.json
openXJV/bin/codelisten_json/GDS.Dienstbezeichnung_1.0.json
openXJV/bin/codelisten_json/GDS.Dokumentklasse_1.3.json
openXJV/bin/codelisten_json/GDS.Dokumentklasse_1.4.json
openXJV/bin/codelisten_json/GDS.Dokumenttyp_3.7.json
openXJV/bin/codelisten_json/GDS.Dokumenttyp_3.8.json
openXJV/bin/codelisten_json/GDS.Entscheidungsart_1.0.json
openXJV/bin/codelisten_json/GDS.Ereignis_1.10.json
openXJV/bin/codelisten_json/GDS.Ereignis_1.11.json
openXJV/bin/codelisten_json/GDS.Ereignis_1.9.json
openXJV/bin/codelisten_json/GDS.FachlicherZusammenhang_1.0.json
openXJV/bin/codelisten_json/GDS.Familienstand_2.0.json
openXJV/bin/codelisten_json/GDS.Fehlercodes_1.0.json
openXJV/bin/codelisten_json/GDS.Finanzbehoerden_1.0.json
openXJV/bin/codelisten_json/GDS.Forderungsteil_1.0.json
openXJV/bin/codelisten_json/GDS.Geheimhaltungsgrad_1.0.json
openXJV/bin/codelisten_json/GDS.Gerichte_3.5.json
openXJV/bin/codelisten_json/GDS.Gerichte_3.6.json
openXJV/bin/codelisten_json/GDS.Geschlecht_2.1.json
openXJV/bin/codelisten_json/GDS.Intervall_2.0.json
openxjv-0.8.8.1.dist-info/licenses/LICENSE
openxjv-0.8.8.1.dist-info/METADATA
openxjv-0.8.8.1.dist-info/WHEEL
openxjv-0.8.8.1.dist-info/entry_points.txt
openxjv-0.8.8.1.dist-info/top_level.txt
openxjv-0.8.8.1.dist-info/RECORD
