Metadata-Version: 2.4
Name: openXJV
Version: 0.8.8.1
Summary: openXJV - open XJustiz Viewer
Home-page: https://openxjv.de
Author: Björn Seipel
Author-email: support@digidigital.de
Project-URL: GitHub, https://github.com/digidigital/openXJV
Project-URL: Bug Tracker, https://github.com/digidigital/openXJV/issues
Keywords: XJustiz-Viewer,XJustiz,eBO,beBPo,beA,beN,EGVP,ERV
Classifier: Programming Language :: Python :: 3
Classifier: License :: OSI Approved :: GNU General Public License v3 (GPLv3)
Classifier: Operating System :: OS Independent
Classifier: Topic :: Office/Business
Classifier: Development Status :: 5 - Production/Stable
Classifier: Intended Audience :: Legal Industry
Classifier: Natural Language :: German
Requires-Python: >=3.10
License-File: LICENSE
Requires-Dist: docx2txt
Requires-Dist: pillow
Requires-Dist: fpdf2
Requires-Dist: numpy
Requires-Dist: pypdfium2>=4.28.0
Requires-Dist: orjson
Requires-Dist: appdirs
Requires-Dist: darkdetect
Requires-Dist: lxml
Requires-Dist: pikepdf
Requires-Dist: PySide6
Requires-Dist: PySide6-Addons
Dynamic: license-file
